pyrogram/__init__.py
pyrogram/client.py
pyrogram/dispatcher.py
pyrogram/emoji.py
pyrogram/file_id.py
pyrogram/filters.py
pyrogram/mime_types.py
pyrogram/py.typed
pyrogram/sync.py
pyrogram/utils.py
pyrogram/connection/__init__.py
pyrogram/connection/connection.py
pyrogram/connection/transport/__init__.py
pyrogram/connection/transport/tcp/__init__.py
pyrogram/connection/transport/tcp/tcp.py
pyrogram/connection/transport/tcp/tcp_abridged.py
pyrogram/connection/transport/tcp/tcp_abridged_o.py
pyrogram/connection/transport/tcp/tcp_full.py
pyrogram/connection/transport/tcp/tcp_intermediate.py
pyrogram/connection/transport/tcp/tcp_intermediate_o.py
pyrogram/crypto/__init__.py
pyrogram/crypto/aes.py
pyrogram/crypto/mtproto.py
pyrogram/crypto/prime.py
pyrogram/crypto/rsa.py
pyrogram/enums/__init__.py
pyrogram/enums/auto_name.py
pyrogram/enums/business_schedule.py
pyrogram/enums/chat_action.py
pyrogram/enums/chat_event_action.py
pyrogram/enums/chat_join_type.py
pyrogram/enums/chat_member_status.py
pyrogram/enums/chat_members_filter.py
pyrogram/enums/chat_type.py
pyrogram/enums/client_platform.py
pyrogram/enums/folder_color.py
pyrogram/enums/message_entity_type.py
pyrogram/enums/message_media_type.py
pyrogram/enums/message_service_type.py
pyrogram/enums/messages_filter.py
pyrogram/enums/next_code_type.py
pyrogram/enums/parse_mode.py
pyrogram/enums/phone_call_discard_reason.py
pyrogram/enums/poll_type.py
pyrogram/enums/privacy_key.py
pyrogram/enums/profile_color.py
pyrogram/enums/reply_color.py
pyrogram/enums/sent_code_type.py
pyrogram/enums/stories_privacy_rules.py
pyrogram/enums/user_status.py
pyrogram/errors/__init__.py
pyrogram/errors/rpc_error.py
pyrogram/handlers/__init__.py
pyrogram/handlers/callback_query_handler.py
pyrogram/handlers/chat_boost_handler.py
pyrogram/handlers/chat_join_request_handler.py
pyrogram/handlers/chat_member_updated_handler.py
pyrogram/handlers/chosen_inline_result_handler.py
pyrogram/handlers/deleted_messages_handler.py
ggnpyro-3.1.32.dist-info/COPYING
ggnpyro-3.1.32.dist-info/COPYING.lesser
ggnpyro-3.1.32.dist-info/METADATA
ggnpyro-3.1.32.dist-info/NOTICE
ggnpyro-3.1.32.dist-info/WHEEL
ggnpyro-3.1.32.dist-info/top_level.txt
ggnpyro-3.1.32.dist-info/RECORD
